{
  "DLSVersion": "2.1.6",
  "Name": "NOR",
  "NameLocation": 0,
  "ChipType": 0,
  "Size": {
    "x": 0.575,
    "y": 0.5
  },
  "Colour": {
    "r": 0.931501031,
    "g": 0.574299932,
    "b": 0.8728558,
    "a": 1
  },
  "InputPins":[
    {
      "Name":"IN",
      "ID":1273376297,
      "Position":{
        "x":-6.62616,
        "y":2.85205
      },
      "BitCount":1,
      "Colour":0,
      "ValueDisplayMode":0
    },
    {
      "Name":"IN",
      "ID":836522280,
      "Position":{
        "x":-6.57666,
        "y":1.64425
      },
      "BitCount":1,
      "Colour":0,
      "ValueDisplayMode":0
    }
  ],
  "OutputPins":[
    {
      "Name":"OUT",
      "ID":1109394044,
      "Position":{
        "x":1.82844,
        "y":2.53525
      },
      "BitCount":1,
      "Colour":0,
      "ValueDisplayMode":0
    }
  ],
  "SubChips":[
    {
      "Name":"OR",
      "ID":214965949,
      "Label":"",
      "Position":{
        "x":-3.94326,
        "y":2.81245
      },
      "OutputPinColourInfo":[{"PinColour":0,"PinID":1013598035}],
      "InternalData":null
    },
    {
      "Name":"NAND",
      "ID":1270740619,
      "Label":"",
      "Position":{
        "x":-0.23075,
        "y":2.39665
      },
      "OutputPinColourInfo":[{"PinColour":0,"PinID":2}],
      "InternalData":null
    },
    {
      "Name":"OR",
      "ID":446134952,
      "Label":"",
      "Position":{
        "x":-3.95316,
        "y":1.76665
      },
      "OutputPinColourInfo":[{"PinColour":0,"PinID":1013598035}],
      "InternalData":null
    },
    {
      "Name":"NOT",
      "ID":228126730,
      "Label":"",
      "Position":{
        "x":-2.28996,
        "y":2.84215
      },
      "OutputPinColourInfo":[{"PinColour":0,"PinID":989469388}],
      "InternalData":null
    },
    {
      "Name":"NOT",
      "ID":472580510,
      "Label":"",
      "Position":{
        "x":-2.31966,
        "y":1.81255
      },
      "OutputPinColourInfo":[{"PinColour":0,"PinID":989469388}],
      "InternalData":null
    }
  ],
  "Wires":[
    {
      "SourcePinAddress":{
        "PinID":1013598035,
        "PinOwnerID":446134952
      },
      "TargetPinAddress":{
        "PinID":2023577524,
        "PinOwnerID":472580510
      },
      "ConnectionType":0,
      "ConnectedWireIndex":-1,
      "ConnectedWireSegmentIndex":-1,
      "Points":[{"x":0.0,"y":0.0},{"x":0.0,"y":0.0}]
    },
    {
      "SourcePinAddress":{
        "PinID":1013598035,
        "PinOwnerID":214965949
      },
      "TargetPinAddress":{
        "PinID":2023577524,
        "PinOwnerID":228126730
      },
      "ConnectionType":0,
      "ConnectedWireIndex":-1,
      "ConnectedWireSegmentIndex":-1,
      "Points":[{"x":0.0,"y":0.0},{"x":0.0,"y":0.0}]
    },
    {
      "SourcePinAddress":{
        "PinID":989469388,
        "PinOwnerID":228126730
      },
      "TargetPinAddress":{
        "PinID":0,
        "PinOwnerID":1270740619
      },
      "ConnectionType":0,
      "ConnectedWireIndex":-1,
      "ConnectedWireSegmentIndex":-1,
      "Points":[{"x":0.0,"y":0.0},{"x":0.0,"y":0.0}]
    },
    {
      "SourcePinAddress":{
        "PinID":989469388,
        "PinOwnerID":472580510
      },
      "TargetPinAddress":{
        "PinID":1,
        "PinOwnerID":1270740619
      },
      "ConnectionType":0,
      "ConnectedWireIndex":-1,
      "ConnectedWireSegmentIndex":-1,
      "Points":[{"x":0.0,"y":0.0},{"x":0.0,"y":0.0}]
    },
    {
      "SourcePinAddress":{
        "PinID":0,
        "PinOwnerID":836522280
      },
      "TargetPinAddress":{
        "PinID":1717478571,
        "PinOwnerID":446134952
      },
      "ConnectionType":0,
      "ConnectedWireIndex":-1,
      "ConnectedWireSegmentIndex":-1,
      "Points":[{"x":0.0,"y":0.0},{"x":0.0,"y":0.0}]
    },
    {
      "SourcePinAddress":{
        "PinID":0,
        "PinOwnerID":1273376297
      },
      "TargetPinAddress":{
        "PinID":1250252211,
        "PinOwnerID":214965949
      },
      "ConnectionType":0,
      "ConnectedWireIndex":-1,
      "ConnectedWireSegmentIndex":-1,
      "Points":[{"x":0.0,"y":0.0},{"x":0.0,"y":0.0}]
    },
    {
      "SourcePinAddress":{
        "PinID":2,
        "PinOwnerID":1270740619
      },
      "TargetPinAddress":{
        "PinID":0,
        "PinOwnerID":1109394044
      },
      "ConnectionType":0,
      "ConnectedWireIndex":-1,
      "ConnectedWireSegmentIndex":-1,
      "Points":[{"x":0.0,"y":0.0},{"x":0.0,"y":0.0}]
    }
  ],
  "Displays": null
}